pytest_httpchain_templates/__init__.py
pytest_httpchain_templates/exceptions.py
pytest_httpchain_templates/expressions.py
pytest_httpchain_templates/substitution.py
pytest_httpchain_templates-0.2.1.dist-info/WHEEL
pytest_httpchain_templates-0.2.1.dist-info/METADATA
pytest_httpchain_templates-0.2.1.dist-info/RECORD
