Metadata-Version: 2.3
Name: pytest-httpchain-templates
Version: 0.2.1
Summary: Templating support for pytest-httpchain
Author: Alexander Eresov
Author-email: Alexander Eresov <aeresov@gmail.com>
Requires-Dist: simpleeval>=1.0.3
Requires-Python: >=3.13
